CorReg/__init__.py
CorReg/hello.py
CorReg-0.0.2.dist-info/LICENSE
CorReg-0.0.2.dist-info/METADATA
CorReg-0.0.2.dist-info/WHEEL
CorReg-0.0.2.dist-info/top_level.txt
CorReg-0.0.2.dist-info/RECORD
