Metadata-Version: 2.1
Name: CorReg
Version: 0.0.2
Summary: The Concept, the Method, the Power
Home-page: http://www.correg.org
Author: Clément Thery
Author-email: corregeous@correg.org
License: UNKNOWN
Platform: UNKNOWN
Classifier: Programming Language :: Python :: 3
Classifier: License :: OSI Approved :: CEA CNRS Inria Logiciel Libre License, version 2.1 (CeCILL-2.1)
Classifier: Operating System :: OS Independent
Classifier: Topic :: Scientific/Engineering :: Mathematics
Requires-Dist: pyttsx3
